greynoise/__init__.py
greynoise/__version__.py
greynoise/exceptions.py
greynoise/util.py
greynoise/api/__init__.py
greynoise/api/filter.py
greynoise/cli/__init__.py
greynoise/cli/decorator.py
greynoise/cli/formatter.py
greynoise/cli/helper.py
greynoise/cli/parameter.py
greynoise/cli/subcommand.py
greynoise/cli/templates/analyze.txt.j2
greynoise/cli/templates/cvedetails.txt.j2
greynoise/cli/templates/gnql_query.txt.j2
greynoise/cli/templates/gnql_stats.txt.j2
greynoise/cli/templates/ip_community.txt.j2
greynoise/cli/templates/ip_context.txt.j2
greynoise/cli/templates/ip_context_result.txt.j2
greynoise/cli/templates/ip_multi_context.txt.j2
greynoise/cli/templates/ip_quick_check.txt.j2
greynoise/cli/templates/macros.txt.j2
greynoise/cli/templates/personadetails.txt.j2
greynoise/cli/templates/riot.txt.j2
greynoise/cli/templates/sensoractivity.txt.j2
greynoise/cli/templates/sensorlist.txt.j2
greynoise/cli/templates/similarity.txt.j2
greynoise/cli/templates/stats.txt.j2
greynoise/cli/templates/timeline.txt.j2
greynoise/cli/templates/timelinehourly.txt.j2
greynoise-3.0.1.dist-info/METADATA
greynoise-3.0.1.dist-info/WHEEL
greynoise-3.0.1.dist-info/entry_points.txt
greynoise-3.0.1.dist-info/licenses/LICENSE
greynoise-3.0.1.dist-info/RECORD
