Metadata-Version: 2.4
Name: greynoise
Version: 3.0.1
Summary: Abstraction to interact with GreyNoise API.
Project-URL: Homepage, https://greynoise.io/
Project-URL: Repository, https://github.com/GreyNoise-Intelligence/pygreynoise
Project-URL: Documentation, https://greynoise.io/
Author-email: GreyNoise Intelligence <support@greynoise.io>
License: MIT
License-File: LICENSE
Keywords: internet,scanning,security,threat intelligence
Classifier: Development Status :: 4 - Beta
Classifier: Intended Audience :: Developers
Classifier: License :: OSI Approved :: MIT License
Classifier: Natural Language :: English
Classifier: Programming Language :: Python
Classifier: Programming Language :: Python :: 3
Classifier: Programming Language :: Python :: 3.8
Classifier: Programming Language :: Python :: 3.9
Classifier: Programming Language :: Python :: 3.10
Classifier: Programming Language :: Python :: 3.11
Classifier: Programming Language :: Python :: 3.12
Classifier: Topic :: Software Development :: Libraries
Requires-Python: >=3.8
Requires-Dist: ansimarkup
Requires-Dist: cachetools
Requires-Dist: click-default-group
Requires-Dist: click-repl
Requires-Dist: click<=8.1.8
Requires-Dist: colorama
Requires-Dist: dict2xml
Requires-Dist: jinja2
Requires-Dist: more-itertools>=8.14.0
Requires-Dist: requests
Requires-Dist: six
